dataPlatformClient/__init__.py
dataPlatformClient/client.py
dataPlatformClient-13.0.dist-info/METADATA
dataPlatformClient-13.0.dist-info/WHEEL
dataPlatformClient-13.0.dist-info/top_level.txt
dataPlatformClient-13.0.dist-info/RECORD
